babypandas/__init__.py
babypandas/bpd.py
babypandas/py.typed
babypandas/utils.py
babypandas-1.0.0.dist-info/WHEEL
babypandas-1.0.0.dist-info/METADATA
babypandas-1.0.0.dist-info/RECORD
