Metadata-Version: 2.3
Name: babypandas
Version: 1.0.0
Summary: A restricted Pandas API for data science learners
Author: Sam Lau, Justin Eldridge, Rod Albuyeh, Aaron Fraenkel, Darren Liu
Author-email: Sam Lau <samlau95@gmail.com>, Justin Eldridge <jeldridge@ucsd.edu>, Rod Albuyeh <ralbuyeh@ucsd.edu>, Aaron Fraenkel <afraenkel@ucsd.edu>, Darren Liu <darrenliu17@gmail.com>
Requires-Dist: numpy>=1,<=2.3.3
Requires-Dist: pandas>=2,<=2.3.3
Requires-Python: >=3.11
